{"name":"Header","type":"header","sections":{"announcement-bar":{"type":"announcement-bar","blocks":{"announcement-bar-0":{"type":"announcement","settings":{"ann-bg":"#000000","ann-txt":"#f0d400","text":"Free Shipping on orders over $99","text_alignment":"center","link":""}}},"block_order":["announcement-bar-0"],"settings":{}},"header":{"type":"header","blocks":{"image_N8wBNy":{"type":"image","settings":{"title":"Crusher Bass","image":"shopify:\/\/shop_images\/desktop_Main_Nav_headphones_38f10a82-9953-47ee-b876-1a86acf552ad.png"}},"image_6Da6km":{"type":"image","settings":{"title":"Product Guide","image":"shopify:\/\/shop_images\/desktop_Main_Nav_headphones_product_guide_7e0aa1d6-e9be-49e3-89c9-7f58efa4619f.png"}},"image_7cTbhw":{"type":"image","settings":{"title":"Join us","image":"shopify:\/\/shop_images\/Screenshot_2024-02-27_at_10.20.13_AM.png"}},"image_qaTFzx":{"type":"image","settings":{"title":"Music with a mission","image":"shopify:\/\/shop_images\/Screenshot_2024-02-27_at_10.19.47_AM.png"}},"image_4DV7dA":{"type":"image","settings":{"title":"ALL-NEW ACTIVE COLLECTION","image":"shopify:\/\/shop_images\/Active_Nav_Tile.png"}},"image_cm6BfK":{"type":"image","settings":{"title":"Earbuds|Product Guide","image":"shopify:\/\/shop_images\/desktop_Main_Nav_earbuds_product_guide_bee0beac-ff9d-42a6-9576-bf7f2ff17b38.png"}},"image_7XPeDf":{"type":"image","settings":{"title":"Limited Edition","image":"shopify:\/\/shop_images\/Merch_Tile_Streetfighter_gaming_2x2_22a091e8-c8de-4537-b1db-cd394eb4cded.png"}},"image_eiyKfA":{"type":"image","disabled":true,"settings":{"title":"Gaming","image":"shopify:\/\/shop_images\/desktop_Main-Nav_gaming.jpg"}},"image_9kL8kR":{"type":"image","settings":{"title":"Triple Threat","image":"shopify:\/\/shop_images\/desktop_Main_Nav_speakers_Limited_Edition_TT.png"}},"image_c4mFbV":{"type":"image","settings":{"title":"Barrel for Party","image":"shopify:\/\/shop_images\/desktop_Main_Nav_speakers_10620aaa-e77b-4d58-9da1-c3709b4590f7.png"}},"image_UqqcXM":{"type":"image","settings":{"title":"Shop All Gaming","image":"shopify:\/\/shop_images\/SkullCandy_Gaming_071120224738-2160.1440.png"}}},"block_order":["image_N8wBNy","image_6Da6km","image_7cTbhw","image_qaTFzx","image_4DV7dA","image_cm6BfK","image_7XPeDf","image_eiyKfA","image_9kL8kR","image_c4mFbV","image_UqqcXM"],"settings":{"color_scheme":"inverse","logo":"shopify:\/\/shop_images\/skdylogosvg.svg","logo-int":"shopify:\/\/shop_images\/US_EN_FLAG.png","logo_width":190,"logo_position":"middle-left","menu_mb":"main-menu","menu":"main-menu","menu_type_desktop":"mega","show_line_separator":true,"enable_sticky_header":false,"margin_bottom":0,"padding_top":8,"padding_bottom":8}}},"order":["announcement-bar","header"]}